iscc_crypto/__init__.py
iscc_crypto/cli.py
iscc_crypto/keys.py
iscc_crypto/nonce.py
iscc_crypto/resolve.py
iscc_crypto/signing.py
iscc_crypto/verifying.py
iscc_crypto-0.5.0.dist-info/METADATA
iscc_crypto-0.5.0.dist-info/WHEEL
iscc_crypto-0.5.0.dist-info/entry_points.txt
iscc_crypto-0.5.0.dist-info/licenses/LICENSE
iscc_crypto-0.5.0.dist-info/RECORD
