Metadata-Version: 2.4
Name: iscc-crypto
Version: 0.5.0
Summary: ISCC-CRYPTO - cryptographic operations for the International Standard Content Code
Project-URL: Documentation, https://crypto.iscc.codes
Project-URL: Repository, https://github.com/iscc/iscc-crypto
Author-email: Titusz <tp@py7.de>
License-Expression: Apache-2.0
License-File: LICENSE
Keywords: EdDSA,content identification,cryptography,iscc,jsc,verifiable credentials
Classifier: Development Status :: 3 - Alpha
Classifier: Intended Audience :: Developers
Classifier: Intended Audience :: Information Technology
Classifier: License :: OSI Approved :: Apache Software License
Classifier: Natural Language :: English
Classifier: Operating System :: OS Independent
Classifier: Programming Language :: Python :: 3.10
Classifier: Programming Language :: Python :: 3.11
Classifier: Programming Language :: Python :: 3.12
Classifier: Programming Language :: Python :: 3.13
Classifier: Topic :: Multimedia :: Graphics
Classifier: Topic :: Multimedia :: Sound/Audio
Classifier: Topic :: Multimedia :: Video
Classifier: Topic :: Security :: Cryptography
Requires-Python: >=3.10
Requires-Dist: base58
Requires-Dist: click
Requires-Dist: cryptography
Requires-Dist: jcs
Requires-Dist: niquests>=3.14.1
Requires-Dist: platformdirs
Requires-Dist: python-dotenv
